[
  {
    "kind": "component",
    "name": "Profile Picture Gauge",
    "description": "A radial gauge chart that wraps around a profile picture. Perfect for showing progress, scores, or metrics with a personalized touch.",
    "author": "Your Name",
    "params": [
      {
        "name": "profileImageUrl",
        "displayName": "Profile Image URL",
        "type": "string",
        "description": "URL of the profile picture to display in the center"
      },
      {
        "name": "value",
        "displayName": "Gauge Value",
        "type": "number",
        "description": "The gauge value from 0-100",
        "default": 75
      },
      {
        "name": "gaugeColor",
        "displayName": "Gauge Color",
        "type": "string",
        "description": "Color of the filled gauge (CSS color format)",
        "default": "rgba(34, 139, 34, 0.8)"
      },
      {
        "name": "trackColor",
        "displayName": "Track Color",
        "type": "string",
        "description": "Color of the empty track background (CSS color format)",
        "default": "rgba(204, 221, 238, 0.3)"
      },
      {
        "name": "centerSize",
        "displayName": "Center Size (%)",
        "type": "number",
        "description": "Size of the center area as percentage of the gauge",
        "default": 80
      },
      {
        "name": "padding",
        "displayName": "Padding",
        "type": "number",
        "description": "Padding around the profile image",
        "default": 4
      }
    ]
  }
]

